{
    "openmcp.showOpenMCP.title": "OpenMCP を表示",
    "openmcp.sidebar.workspace-connection.revealWebviewPanel.title": "接続",
    "openmcp.sidebar.workspace-connection.deleteConnection.title": "接続を削除",
    "openmcp.sidebar.workspace-connection.refresh.title": "更新",
    "openmcp.sidebar.workspace-connection.addConnection.title": "接続を追加",
    "openmcp.sidebar.workspace-connection.openConfiguration.title": "設定を開く",
    "openmcp.sidebar.installed-connection.revealWebviewPanel.title": "接続",
    "openmcp.sidebar.installed-connection.deleteConnection.title": "接続を削除",
    "openmcp.sidebar.installed-connection.refresh.title": "更新",
    "openmcp.sidebar.installed-connection.addConnection.title": "接続を追加",
    "openmcp.sidebar.installed-connection.openConfiguration.title": "設定を開く",
    "openmcp.hook.test-ocr.title": "OCR をテスト",
    "openmcp.sidebar.workspace-connection.view.title": "MCP 接続（ワークスペース）",
    "openmcp.sidebar.installed-connection.view.title": "インストール済み MCP サーバー",
    "openmcp.sidebar.help.view.title": "はじめに・ヘルプ",
    "openmcp.hook.test-news.title": "テストニュースレポート",
    "openmcp.sidebar.installed-connection.changeConnectionName.title": "サーバー名を変更",
    "openmcp.sidebar.workspace-connection.changeConnectionName.title": "サーバー名を変更"
}